usbusiness
