Metadata-Version: 1.2
Name: usbusiness
Version: 0.2.1
Summary: NAICS code business domain classifier and domain utility kit
Home-page: UNKNOWN
Author: Glendon Thompson
Author-email: glendonthompson1@gmail.com
License: MIT
Keywords: naics usa business predict website analytics industry classfication
Platform: UNKNOWN
Classifier: Development Status :: 3 - Alpha
Classifier: Intended Audience :: Developers
Classifier: Topic :: Software Development :: Build Tools
Classifier: License :: OSI Approved :: MIT License
Classifier: Programming Language :: Python :: 2.7
Requires-Python: >=2.7
